{
  "type": "FeatureCollection",
  "features": [
    {
      "type": "Feature",
      "properties": {
        "name": "Lanjut Usia",
        "kategori": "Lanjut Usia",
        "count": 23,
        "level": "Sedang"
      },
      "geometry": {
        "type": "Point",
        "coordinates": [110.2980, -7.5010]
      }
    },
    {
      "type": "Feature",
      "properties": {
        "name": "Disabilitas",
        "kategori": "Disabilitas",
        "count": 2,
        "level": "Rendah"
      },
      "geometry": {
        "type": "Point",
        "coordinates": [110.3030, -7.5075]
      }
    },
    {
      "type": "Feature",
      "properties": {
        "name": "Balita",
        "kategori": "Balita",
        "count": 10,
        "level": "Rendah"
      },
      "geometry": {
        "type": "Point",
        "coordinates": [110.2890, -7.5085]
      }
    }
  ]
}
